{
  "layout": "theme.alternate",
  "sections": {
    "bacb6636-ff65-4a8f-a84a-bedcf9993577": {
      "type": "alternate-main-product",
      "blocks": {
        "463fc9c1-86f1-4014-b280-301779389e7f": {
          "type": "accordeon",
          "settings": {
            "title": "Sizing & Fit",
            "text": "<p>Аккордеон1<\/p>"
          }
        },
        "b424d7b2-d583-4dfb-89b2-630342127e97": {
          "type": "accordeon",
          "settings": {
            "title": "Sizing & Fit",
            "text": "<p>Аккордеон2<\/p>"
          }
        },
        "b9ad42d9-de6d-49ff-8190-8db8564d3768": {
          "type": "accordeon",
          "settings": {
            "title": "Sizing & Fit",
            "text": "<p>Аккордеон3<\/p>"
          }
        }
      },
      "block_order": [
        "463fc9c1-86f1-4014-b280-301779389e7f",
        "b424d7b2-d583-4dfb-89b2-630342127e97",
        "b9ad42d9-de6d-49ff-8190-8db8564d3768"
      ],
      "settings": {
      }
    },
    "6d28f1a5-17be-42be-ab8a-f7294766aa37": {
      "type": "alternate-product-recommendations",
      "settings": {
        "heading": "You may also like",
        "collection": "wool-figures",
        "number_of_products": 4
      }
    }
  },
  "order": [
    "bacb6636-ff65-4a8f-a84a-bedcf9993577",
    "6d28f1a5-17be-42be-ab8a-f7294766aa37"
  ]
}